MANIFEST.in
README
setup.py
django_settingsjs.egg-info/PKG-INFO
django_settingsjs.egg-info/SOURCES.txt
django_settingsjs.egg-info/dependency_links.txt
django_settingsjs.egg-info/top_level.txt
settingsjs/__init__.py
settingsjs/signals.py
settingsjs/urls.py
settingsjs/views.py
settingsjs/templates/settingsjs/settings.js