Metadata-Version: 1.0
Name: django-settingsjs
Version: 0.1.4
Summary: Configurable Javascript settings in Django.
Home-page: http://github.com/incuna/django-settingsjs/
Author: Incuna Ltd
Author-email: admin@incuna.com
License: UNKNOWN
Platform: UNKNOWN
